{"order":2,"op":"command","command":"buildInfo","ns":"store.$cmd","request_data":{"buildInfo":1},"reply_data":{"allocator":"tcmalloc","bits":64,"buildEnvironment":{"cc":"/opt/mongodbtoolchain/v2/bin/gcc: gcc (GCC) 5.4.0","ccflags":"-fno-omit-frame-pointer -fno-strict-aliasing -ggdb -pthread -Wall -Wsign-compare -Wno-unknown-pragmas -Winvalid-pch -Werror -O2 -Wno-unused-local-typedefs -Wno-unused-function -Wno-deprecated-declarations -Wno-unused-but-set-variable -Wno-missing-braces -fstack-protector-strong -fno-builtin-memcmp","cxx":"/opt/mongodbtoolchain/v2/bin/g++: g++ (GCC) 5.4.0","cxxflags":"-Woverloaded-virtual -Wno-maybe-uninitialized -std=c++11","distarch":"x86_64","distmod":"debian81","linkflags":"-pthread -Wl,-z,now -rdynamic -Wl,--fatal-warnings -fstack-protector-strong -fuse-ld=gold -Wl,--build-id -Wl,-z,noexecstack -Wl,--warn-execstack -Wl,-z,relro","target_arch":"x86_64","target_os":"linux"},"debug":false,"gitVersion":"078f28920cb24de0dd479b5ea6c66c644f6326e9","javascriptEngine":"mozjs","maxBsonObjectSize":16777216,"modules":[],"ok":1.0,"openssl":{"compiled":"OpenSSL 1.0.1t  3 May 2016","running":"OpenSSL 1.0.1t  3 May 2016"},"storageEngines":["devnull","ephemeralForTest","mmapv1","wiredTiger"],"sysInfo":"deprecated","version":"3.4.10","versionArray":[3,4,10,0]},"nreturned":1,"played_at":"2018-08-14T16:29:57.719081491+02:00","play_at":"2018-08-14T16:29:57.718569063+02:00","playbacklag_us":512,"connection_num":2,"latency_us":888,"seen":"2018-08-14T14:25:00.864868Z","request_id":1970}
{"order":4,"op":"insert","ns":"store.$cmd","request_data":{"documents":[{"_class":"org.jhipster.store.domain.Product","_id":{"$oid":"5b72e63f0274390001fce767"},"name":"prod2","price":"2.33"}],"insert":"product","ordered":true},"reply_data":{"n":0,"ok":1.0,"writeErrors":[{"code":11000,"errmsg":"E11000 duplicate key error collection: store.product index: _id_ dup key: { : ObjectId('5b72e63f0274390001fce767') }","index":0}]},"nreturned":1,"played_at":"2018-08-14T16:30:00.636009525+02:00","play_at":"2018-08-14T16:30:00.635307063+02:00","playbacklag_us":702,"connection_num":2,"latency_us":1439,"errors":[{}],"seen":"2018-08-14T14:25:03.781606Z","request_id":1971}
{"order":6,"op":"command","command":"count","ns":"store.$cmd","request_data":{"count":"product","query":{}},"reply_data":{"n":2,"ok":1.0},"nreturned":1,"played_at":"2018-08-14T16:30:00.660566966+02:00","play_at":"2018-08-14T16:30:00.660086063+02:00","playbacklag_us":480,"connection_num":2,"latency_us":1086,"seen":"2018-08-14T14:25:03.806385Z","request_id":1972}
{"order":8,"op":"command","command":"find","ns":"store.$cmd","request_data":{"filter":{},"find":"product","limit":20,"sort":{"_id":1}},"reply_data":{"cursor":{"firstBatch":[{"_class":"org.jhipster.store.domain.Product","_id":{"$oid":"5b72c5b20274390001fce762"},"name":"prod1","price":"19.99"},{"_class":"org.jhipster.store.domain.Product","_id":{"$oid":"5b72e63f0274390001fce767"},"name":"prod2","price":"2.33"}],"id":{"$numberLong":"0"},"ns":"store.product"},"ok":1.0},"nreturned":1,"played_at":"2018-08-14T16:30:00.662241916+02:00","play_at":"2018-08-14T16:30:00.661081063+02:00","playbacklag_us":1160,"connection_num":2,"latency_us":876,"seen":"2018-08-14T14:25:03.80738Z","request_id":1973}
